example/fpga_projects_hdl/LAB1/legacy/10_seven_segment/original/seg_decoder.v

module seg_decoder( bcd, seg_data );

input [3:0] bcd;
output [7:0] seg_data;

reg [7:0] seg_data;

always @(bcd)
begin
	case(bcd)
		4'b0000 : seg_data = 8'b1111_1100;
		4'b0001 : seg_data = 8'b0110_0000;
		4'b0010 : seg_data = 8'b1101_1010;
		4'b0011 : seg_data = 8'b1111_0010;
		4'b0100 : seg_data = 8'b0110_0110;
		4'b0101 : seg_data = 8'b1011_0110;
		4'b0110 : seg_data = 8'b1011_1110;
		4'b0111 : seg_data = 8'b1110_0000;
		4'b1000 : seg_data = 8'b1111_1110;
		4'b1001 : seg_data = 8'b1111_0110;
		4'b1010 : seg_data = 8'b1110_1110;
		4'b1011 : seg_data = 8'b0011_1110;
		4'b1100 : seg_data = 8'b1001_1100;
		4'b1101 : seg_data = 8'b0111_1010;
		4'b1110 : seg_data = 8'b1001_1110;
		4'b1111 : seg_data = 8'b1000_1110;
	endcase

end

endmodule

example/fpga_projects_hdl/LAB1/common/tb/tb_seg_decoder.sv
`timescale 1ns/1ps
module tb_seg_decoder;
  reg [3:0] bcd; wire [7:0] seg_data; reg [7:0] digits[0:15]; seg_decoder dut(bcd,seg_data);
  integer n,checked=0;
  reg [7:0] expected;
  initial begin
    $dumpfile("wave.vcd"); $dumpvars(0,tb_seg_decoder);
    digits[0]=8'hfc;
    digits[1]=8'h60;
    digits[2]=8'hda;
    digits[3]=8'hf2;
    digits[4]=8'h66;
    digits[5]=8'hb6;
    digits[6]=8'hbe;
    digits[7]=8'he0;
    digits[8]=8'hfe;
    digits[9]=8'hf6;
    digits[10]=8'hee;
    digits[11]=8'h3e;
    digits[12]=8'h9c;
    digits[13]=8'h7a;
    digits[14]=8'h9e;
    digits[15]=8'h8e;
    for(n=0;n<16;n=n+1) begin
      bcd=n;
      expected=digits[n];
      #10;
      if (seg_data !== expected)
        $fatal(1,"FAIL seg_decoder vector=%0d expected=%h actual=%h",n,expected,seg_data);
      checked=checked+1;
    end
    if(checked!=16) $fatal(1,"Incomplete test");
    $display("LAB1_PASS seg_decoder cases=%0d",checked);
    $finish;
  end
  initial begin #100000; $fatal(1,"Watchdog"); end
endmodule

example/fpga_projects_hdl/LAB1/vivado_2026_1/10_seven_segment/evidence/gui-wave.vcd
$date
   Thu Sep 10 14:16:54 2026
$end

$version
  2026.1
  $dumpfile ("wave.vcd") 
$end

$timescale
  1ps
$end

$scope module tb_seg_decoder $end
$var reg 4 ! bcd [3:0] $end
$var wire 8 " seg_data [7:0] $end
$var integer 32 # n [31:0] $end
$var integer 32 $ checked [31:0] $end
$var reg 8 % expected [7:0] $end
$scope module dut $end
$var wire 4 & bcd [3:0] $end
$var reg 8 ' seg_data [7:0] $end
$upscope $end
$upscope $end
$enddefinitions $end

#0
$dumpvars
b0 !
b11111100 "
b0 #
b0 $
b11111100 %
b0 &
b11111100 '
$end

#10000
b1 !
b1100000 "
b1 #
b1 $
b1100000 %
b1 &
b1100000 '

#20000
b10 !
b11011010 "
b10 #
b10 $
b11011010 %
b10 &
b11011010 '

#30000
b11 !
b11110010 "
b11 #
b11 $
b11110010 %
b11 &
b11110010 '

#40000
b100 !
b1100110 "
b100 #
b100 $
b1100110 %
b100 &
b1100110 '

#50000
b101 !
b10110110 "
b101 #
b101 $
b10110110 %
b101 &
b10110110 '

#60000
b110 !
b10111110 "
b110 #
b110 $
b10111110 %
b110 &
b10111110 '

#70000
b111 !
b11100000 "
b111 #
b111 $
b11100000 %
b111 &
b11100000 '

#80000
b1000 !
b11111110 "
b1000 #
b1000 $
b11111110 %
b1000 &
b11111110 '

#90000
b1001 !
b11110110 "
b1001 #
b1001 $
b11110110 %
b1001 &
b11110110 '

#100000
b1010 !
b11101110 "
b1010 #
b1010 $
b11101110 %
b1010 &
b11101110 '

#110000
b1011 !
b111110 "
b1011 #
b1011 $
b111110 %
b1011 &
b111110 '

#120000
b1100 !
b10011100 "
b1100 #
b1100 $
b10011100 %
b1100 &
b10011100 '

#130000
b1101 !
b1111010 "
b1101 #
b1101 $
b1111010 %
b1101 &
b1111010 '

#140000
b1110 !
b10011110 "
b1110 #
b1110 $
b10011110 %
b1110 &
b10011110 '

#150000
b1111 !
b10001110 "
b1111 #
b1111 $
b10001110 %
b1111 &
b10001110 '

#160000
b10000 #
b10000 $
