example/fpga_projects_hdl/LAB1/legacy/02_full_adder/original/half_adder.v

module half_adder(
a, b,
s, c
);

input a, b;
output s, c;

reg s, c;

always @(a or b)
begin
	if (a==b) s = 0;
	else s = 1;
	
	if (a == 1 && b == 1) c = 1;
	else c = 0;
end

endmodule

example/fpga_projects_hdl/LAB1/legacy/02_full_adder/original/full_adder.v

module full_adder(
a, b, cin,
s, cout
);

input a, b, cin;
output s, cout;

wire s, cout;
wire reg_c1, reg_c2;
wire reg_sum;

half_adder u1 (.a(a), .b(b), .s(reg_sum), .c(reg_c1));
half_adder u2 (.a(cin), .b(reg_sum), .s(s), .c(reg_c2));

assign cout = reg_c1 | reg_c2;

endmodule

example/fpga_projects_hdl/LAB1/common/tb/tb_full_adder.sv
`timescale 1ns/1ps
module tb_full_adder;
  reg a,b,cin; wire s,cout; full_adder dut(a,b,cin,s,cout);
  integer n,checked=0;
  reg [1:0] expected;
  initial begin
    $dumpfile("wave.vcd"); $dumpvars(0,tb_full_adder);

    for(n=0;n<8;n=n+1) begin
      {a,b,cin}=n;
      expected=int'(a)+int'(b)+int'(cin);
      #10;
      if ({cout,s} !== expected)
        $fatal(1,"FAIL full_adder vector=%0d expected=%h actual=%h",n,expected,{cout,s});
      checked=checked+1;
    end
    if(checked!=8) $fatal(1,"Incomplete test");
    $display("LAB1_PASS full_adder cases=%0d",checked);
    $finish;
  end
  initial begin #100000; $fatal(1,"Watchdog"); end
endmodule

example/fpga_projects_hdl/LAB1/legacy/02_full_adder/evidence/waveform-source.vcd
$date
   Thu Sep 10 02:42:30 2026
$end

$version
  2026.1
  $dumpfile ("wave.vcd") 
$end

$timescale
  1ps
$end

$scope module tb_full_adder $end
$var reg 1 ! a $end
$var reg 1 " b $end
$var reg 1 # cin $end
$var wire 1 $ s $end
$var wire 1 % cout $end
$var integer 32 & n [31:0] $end
$var integer 32 ' checked [31:0] $end
$var reg 2 ( expected [1:0] $end
$scope module dut $end
$var wire 1 ) a $end
$var wire 1 * b $end
$var wire 1 + cin $end
$var wire 1 $ s $end
$var wire 1 % cout $end
$var wire 1 , reg_c1 $end
$var wire 1 - reg_c2 $end
$var wire 1 . reg_sum $end
$scope module u1 $end
$var wire 1 ) a $end
$var wire 1 * b $end
$var reg 1 / s $end
$var reg 1 0 c $end
$upscope $end
$scope module u2 $end
$var wire 1 + a $end
$var wire 1 . b $end
$var reg 1 1 s $end
$var reg 1 2 c $end
$upscope $end
$upscope $end
$upscope $end
$enddefinitions $end

#0
$dumpvars
0!
0"
0#
0$
0%
b0 &
b0 '
b0 (
0)
0*
0+
0,
0-
0.
0/
00
01
02
$end

#10000
1#
1$
b1 &
b1 '
b1 (
1+
11

#20000
1"
0#
b10 &
b10 '
1*
0+
1.
1/

#30000
1#
0$
1%
b11 &
b11 '
b10 (
1+
1-
01
12

#40000
1!
0"
0#
1$
0%
b100 &
b100 '
b1 (
1)
0*
0+
0-
11
02

#50000
1#
0$
1%
b101 &
b101 '
b10 (
1+
1-
01
12

#60000
1"
0#
b110 &
b110 '
1*
0+
1,
0-
0.
0/
10
02

#70000
1#
1$
b111 &
b111 '
b11 (
1+
11

#80000
b1000 &
b1000 '
