example/fpga_projects_hdl/LAB1/legacy/04_subtractor4/original/sub_4bit.v

module sub_4bit(a, b, d, bor);

input [3:0] a, b;

output [3:0] d;
output bor;

reg [3:0] d;
reg bor;

always @(a or b)
begin
	d = a - b;
	
	if (a > b)	bor = 1'b0;
	else		bor = 1'b1;
end

endmodule

example/fpga_projects_hdl/LAB1/common/tb/tb_sub_4bit.sv
`timescale 1ns/1ps
module tb_sub_4bit;
  reg [3:0] a,b; wire [3:0] d; wire bor; sub_4bit dut(a,b,d,bor);
  integer n,checked=0;
  reg [4:0] expected;
  initial begin
    $dumpfile("wave.vcd"); $dumpvars(0,tb_sub_4bit);

    for(n=0;n<256;n=n+1) begin
      {a,b}=n;
      expected=(((n/16)<(n%16)) ? 16 : 0) | (((n/16)-(n%16)) & 15);
      #10;
      if ({bor,d} !== expected)
        $fatal(1,"FAIL sub_4bit vector=%0d expected=%h actual=%h",n,expected,{bor,d});
      checked=checked+1;
    end
    if(checked!=256) $fatal(1,"Incomplete test");
    $display("LAB1_PASS sub_4bit cases=%0d",checked);
    $finish;
  end
  initial begin #100000; $fatal(1,"Watchdog"); end
endmodule

example/fpga_projects_hdl/LAB1/vivado_2026_1/04_subtractor4/evidence/vscode-wave.vcd
$date
   Thu Sep 10 04:07:11 2026
$end

$version
  2026.1
  $dumpfile ("wave.vcd") 
$end

$timescale
  1ps
$end

$scope module tb_sub_4bit $end
$var reg 4 ! a [3:0] $end
$var reg 4 " b [3:0] $end
$var wire 4 # d [3:0] $end
$var wire 1 $ bor $end
$var integer 32 % n [31:0] $end
$var integer 32 & checked [31:0] $end
$var reg 5 ' expected [4:0] $end
$scope module dut $end
$var wire 4 ( a [3:0] $end
$var wire 4 ) b [3:0] $end
$var wire 4 # d [3:0] $end
$var wire 1 $ bor $end
$upscope $end
$upscope $end
$enddefinitions $end

#0
$dumpvars
b0 !
b0 "
b0 #
0$
b0 %
b0 &
b0 '
b0 (
b0 )
$end

#10000
b1 "
b1111 #
1$
b1 %
b1 &
b11111 '
b1 )

#20000
b10 "
b1110 #
b10 %
b10 &
b11110 '
b10 )

#30000
b11 "
b1101 #
b11 %
b11 &
b11101 '
b11 )

#40000
b100 "
b1100 #
b100 %
b100 &
b11100 '
b100 )

#50000
b101 "
b1011 #
b101 %
b101 &
b11011 '
b101 )

#60000
b110 "
b1010 #
b110 %
b110 &
b11010 '
b110 )

#70000
b111 "
b1001 #
b111 %
b111 &
b11001 '
b111 )

#80000
b1000 "
b1000 #
b1000 %
b1000 &
b11000 '
b1000 )

#90000
b1001 "
b111 #
b1001 %
b1001 &
b10111 '
b1001 )

#100000
b1010 "
b110 #
b1010 %
b1010 &
b10110 '
b1010 )

#110000
b1011 "
b101 #
b1011 %
b1011 &
b10101 '
b1011 )

#120000
b1100 "
b100 #
b1100 %
b1100 &
b10100 '
b1100 )

#130000
b1101 "
b11 #
b1101 %
b1101 &
b10011 '
b1101 )

#140000
b1110 "
b10 #
b1110 %
b1110 &
b10010 '
b1110 )

#150000
b1111 "
b1 #
b1111 %
b1111 &
b10001 '
b1111 )

#160000
b1 !
b0 "
0$
b10000 %
b10000 &
b1 '
b1 (
b0 )

#170000
b1 "
b0 #
b10001 %
b10001 &
b0 '
b1 )

#180000
b10 "
b1111 #
1$
b10010 %
b10010 &
b11111 '
b10 )

#190000
b11 "
b1110 #
b10011 %
b10011 &
b11110 '
b11 )

#200000
b100 "
b1101 #
b10100 %
b10100 &
b11101 '
b100 )

#210000
b101 "
b1100 #
b10101 %
b10101 &
b11100 '
b101 )

#220000
b110 "
b1011 #
b10110 %
b10110 &
b11011 '
b110 )

#230000
b111 "
b1010 #
b10111 %
b10111 &
b11010 '
b111 )

#240000
b1000 "
b1001 #
b11000 %
b11000 &
b11001 '
b1000 )

#250000
b1001 "
b1000 #
b11001 %
b11001 &
b11000 '
b1001 )

#260000
b1010 "
b111 #
b11010 %
b11010 &
b10111 '
b1010 )

#270000
b1011 "
b110 #
b11011 %
b11011 &
b10110 '
b1011 )

#280000
b1100 "
b101 #
b11100 %
b11100 &
b10101 '
b1100 )

#290000
b1101 "
b100 #
b11101 %
b11101 &
b10100 '
b1101 )

#300000
b1110 "
b11 #
b11110 %
b11110 &
b10011 '
b1110 )

#310000
b1111 "
b10 #
b11111 %
b11111 &
b10010 '
b1111 )

#320000
b10 !
b0 "
0$
b100000 %
b100000 &
b10 '
b10 (
b0 )

#330000
b1 "
b1 #
b100001 %
b100001 &
b1 '
b1 )

#340000
b10 "
b0 #
b100010 %
b100010 &
b0 '
b10 )

#350000
b11 "
b1111 #
1$
b100011 %
b100011 &
b11111 '
b11 )

#360000
b100 "
b1110 #
b100100 %
b100100 &
b11110 '
b100 )

#370000
b101 "
b1101 #
b100101 %
b100101 &
b11101 '
b101 )

#380000
b110 "
b1100 #
b100110 %
b100110 &
b11100 '
b110 )

#390000
b111 "
b1011 #
b100111 %
b100111 &
b11011 '
b111 )

#400000
b1000 "
b1010 #
b101000 %
b101000 &
b11010 '
b1000 )

#410000
b1001 "
b1001 #
b101001 %
b101001 &
b11001 '
b1001 )

#420000
b1010 "
b1000 #
b101010 %
b101010 &
b11000 '
b1010 )

#430000
b1011 "
b111 #
b101011 %
b101011 &
b10111 '
b1011 )

#440000
b1100 "
b110 #
b101100 %
b101100 &
b10110 '
b1100 )

#450000
b1101 "
b101 #
b101101 %
b101101 &
b10101 '
b1101 )

#460000
b1110 "
b100 #
b101110 %
b101110 &
b10100 '
b1110 )

#470000
b1111 "
b11 #
b101111 %
b101111 &
b10011 '
b1111 )

#480000
b11 !
b0 "
0$
b110000 %
b110000 &
b11 '
b11 (
b0 )

#490000
b1 "
b10 #
b110001 %
b110001 &
b10 '
b1 )

#500000
b10 "
b1 #
b110010 %
b110010 &
b1 '
b10 )

#510000
b11 "
b0 #
b110011 %
b110011 &
b0 '
b11 )

#520000
b100 "
b1111 #
1$
b110100 %
b110100 &
b11111 '
b100 )

#530000
b101 "
b1110 #
b110101 %
b110101 &
b11110 '
b101 )

#540000
b110 "
b1101 #
b110110 %
b110110 &
b11101 '
b110 )

#550000
b111 "
b1100 #
b110111 %
b110111 &
b11100 '
b111 )

#560000
b1000 "
b1011 #
b111000 %
b111000 &
b11011 '
b1000 )

#570000
b1001 "
b1010 #
b111001 %
b111001 &
b11010 '
b1001 )

#580000
b1010 "
b1001 #
b111010 %
b111010 &
b11001 '
b1010 )

#590000
b1011 "
b1000 #
b111011 %
b111011 &
b11000 '
b1011 )

#600000
b1100 "
b111 #
b111100 %
b111100 &
b10111 '
b1100 )

#610000
b1101 "
b110 #
b111101 %
b111101 &
b10110 '
b1101 )

#620000
b1110 "
b101 #
b111110 %
b111110 &
b10101 '
b1110 )

#630000
b1111 "
b100 #
b111111 %
b111111 &
b10100 '
b1111 )

#640000
b100 !
b0 "
0$
b1000000 %
b1000000 &
b100 '
b100 (
b0 )

#650000
b1 "
b11 #
b1000001 %
b1000001 &
b11 '
b1 )

#660000
b10 "
b10 #
b1000010 %
b1000010 &
b10 '
b10 )

#670000
b11 "
b1 #
b1000011 %
b1000011 &
b1 '
b11 )

#680000
b100 "
b0 #
b1000100 %
b1000100 &
b0 '
b100 )

#690000
b101 "
b1111 #
1$
b1000101 %
b1000101 &
b11111 '
b101 )

#700000
b110 "
b1110 #
b1000110 %
b1000110 &
b11110 '
b110 )

#710000
b111 "
b1101 #
b1000111 %
b1000111 &
b11101 '
b111 )

#720000
b1000 "
b1100 #
b1001000 %
b1001000 &
b11100 '
b1000 )

#730000
b1001 "
b1011 #
b1001001 %
b1001001 &
b11011 '
b1001 )

#740000
b1010 "
b1010 #
b1001010 %
b1001010 &
b11010 '
b1010 )

#750000
b1011 "
b1001 #
b1001011 %
b1001011 &
b11001 '
b1011 )

#760000
b1100 "
b1000 #
b1001100 %
b1001100 &
b11000 '
b1100 )

#770000
b1101 "
b111 #
b1001101 %
b1001101 &
b10111 '
b1101 )

#780000
b1110 "
b110 #
b1001110 %
b1001110 &
b10110 '
b1110 )

#790000
b1111 "
b101 #
b1001111 %
b1001111 &
b10101 '
b1111 )

#800000
b101 !
b0 "
0$
b1010000 %
b1010000 &
b101 '
b101 (
b0 )

#810000
b1 "
b100 #
b1010001 %
b1010001 &
b100 '
b1 )

#820000
b10 "
b11 #
b1010010 %
b1010010 &
b11 '
b10 )

#830000
b11 "
b10 #
b1010011 %
b1010011 &
b10 '
b11 )

#840000
b100 "
b1 #
b1010100 %
b1010100 &
b1 '
b100 )

#850000
b101 "
b0 #
b1010101 %
b1010101 &
b0 '
b101 )

#860000
b110 "
b1111 #
1$
b1010110 %
b1010110 &
b11111 '
b110 )

#870000
b111 "
b1110 #
b1010111 %
b1010111 &
b11110 '
b111 )

#880000
b1000 "
b1101 #
b1011000 %
b1011000 &
b11101 '
b1000 )

#890000
b1001 "
b1100 #
b1011001 %
b1011001 &
b11100 '
b1001 )

#900000
b1010 "
b1011 #
b1011010 %
b1011010 &
b11011 '
b1010 )

#910000
b1011 "
b1010 #
b1011011 %
b1011011 &
b11010 '
b1011 )

#920000
b1100 "
b1001 #
b1011100 %
b1011100 &
b11001 '
b1100 )

#930000
b1101 "
b1000 #
b1011101 %
b1011101 &
b11000 '
b1101 )

#940000
b1110 "
b111 #
b1011110 %
b1011110 &
b10111 '
b1110 )

#950000
b1111 "
b110 #
b1011111 %
b1011111 &
b10110 '
b1111 )

#960000
b110 !
b0 "
0$
b1100000 %
b1100000 &
b110 '
b110 (
b0 )

#970000
b1 "
b101 #
b1100001 %
b1100001 &
b101 '
b1 )

#980000
b10 "
b100 #
b1100010 %
b1100010 &
b100 '
b10 )

#990000
b11 "
b11 #
b1100011 %
b1100011 &
b11 '
b11 )

#1000000
b100 "
b10 #
b1100100 %
b1100100 &
b10 '
b100 )

#1010000
b101 "
b1 #
b1100101 %
b1100101 &
b1 '
b101 )

#1020000
b110 "
b0 #
b1100110 %
b1100110 &
b0 '
b110 )

#1030000
b111 "
b1111 #
1$
b1100111 %
b1100111 &
b11111 '
b111 )

#1040000
b1000 "
b1110 #
b1101000 %
b1101000 &
b11110 '
b1000 )

#1050000
b1001 "
b1101 #
b1101001 %
b1101001 &
b11101 '
b1001 )

#1060000
b1010 "
b1100 #
b1101010 %
b1101010 &
b11100 '
b1010 )

#1070000
b1011 "
b1011 #
b1101011 %
b1101011 &
b11011 '
b1011 )

#1080000
b1100 "
b1010 #
b1101100 %
b1101100 &
b11010 '
b1100 )

#1090000
b1101 "
b1001 #
b1101101 %
b1101101 &
b11001 '
b1101 )

#1100000
b1110 "
b1000 #
b1101110 %
b1101110 &
b11000 '
b1110 )

#1110000
b1111 "
b111 #
b1101111 %
b1101111 &
b10111 '
b1111 )

#1120000
b111 !
b0 "
0$
b1110000 %
b1110000 &
b111 '
b111 (
b0 )

#1130000
b1 "
b110 #
b1110001 %
b1110001 &
b110 '
b1 )

#1140000
b10 "
b101 #
b1110010 %
b1110010 &
b101 '
b10 )

#1150000
b11 "
b100 #
b1110011 %
b1110011 &
b100 '
b11 )

#1160000
b100 "
b11 #
b1110100 %
b1110100 &
b11 '
b100 )

#1170000
b101 "
b10 #
b1110101 %
b1110101 &
b10 '
b101 )

#1180000
b110 "
b1 #
b1110110 %
b1110110 &
b1 '
b110 )

#1190000
b111 "
b0 #
b1110111 %
b1110111 &
b0 '
b111 )

#1200000
b1000 "
b1111 #
1$
b1111000 %
b1111000 &
b11111 '
b1000 )

#1210000
b1001 "
b1110 #
b1111001 %
b1111001 &
b11110 '
b1001 )

#1220000
b1010 "
b1101 #
b1111010 %
b1111010 &
b11101 '
b1010 )

#1230000
b1011 "
b1100 #
b1111011 %
b1111011 &
b11100 '
b1011 )

#1240000
b1100 "
b1011 #
b1111100 %
b1111100 &
b11011 '
b1100 )

#1250000
b1101 "
b1010 #
b1111101 %
b1111101 &
b11010 '
b1101 )

#1260000
b1110 "
b1001 #
b1111110 %
b1111110 &
b11001 '
b1110 )

#1270000
b1111 "
b1000 #
b1111111 %
b1111111 &
b11000 '
b1111 )

#1280000
b1000 !
b0 "
0$
b10000000 %
b10000000 &
b1000 '
b1000 (
b0 )

#1290000
b1 "
b111 #
b10000001 %
b10000001 &
b111 '
b1 )

#1300000
b10 "
b110 #
b10000010 %
b10000010 &
b110 '
b10 )

#1310000
b11 "
b101 #
b10000011 %
b10000011 &
b101 '
b11 )

#1320000
b100 "
b100 #
b10000100 %
b10000100 &
b100 '
b100 )

#1330000
b101 "
b11 #
b10000101 %
b10000101 &
b11 '
b101 )

#1340000
b110 "
b10 #
b10000110 %
b10000110 &
b10 '
b110 )

#1350000
b111 "
b1 #
b10000111 %
b10000111 &
b1 '
b111 )

#1360000
b1000 "
b0 #
b10001000 %
b10001000 &
b0 '
b1000 )

#1370000
b1001 "
b1111 #
1$
b10001001 %
b10001001 &
b11111 '
b1001 )

#1380000
b1010 "
b1110 #
b10001010 %
b10001010 &
b11110 '
b1010 )

#1390000
b1011 "
b1101 #
b10001011 %
b10001011 &
b11101 '
b1011 )

#1400000
b1100 "
b1100 #
b10001100 %
b10001100 &
b11100 '
b1100 )

#1410000
b1101 "
b1011 #
b10001101 %
b10001101 &
b11011 '
b1101 )

#1420000
b1110 "
b1010 #
b10001110 %
b10001110 &
b11010 '
b1110 )

#1430000
b1111 "
b1001 #
b10001111 %
b10001111 &
b11001 '
b1111 )

#1440000
b1001 !
b0 "
0$
b10010000 %
b10010000 &
b1001 '
b1001 (
b0 )

#1450000
b1 "
b1000 #
b10010001 %
b10010001 &
b1000 '
b1 )

#1460000
b10 "
b111 #
b10010010 %
b10010010 &
b111 '
b10 )

#1470000
b11 "
b110 #
b10010011 %
b10010011 &
b110 '
b11 )

#1480000
b100 "
b101 #
b10010100 %
b10010100 &
b101 '
b100 )

#1490000
b101 "
b100 #
b10010101 %
b10010101 &
b100 '
b101 )

#1500000
b110 "
b11 #
b10010110 %
b10010110 &
b11 '
b110 )

#1510000
b111 "
b10 #
b10010111 %
b10010111 &
b10 '
b111 )

#1520000
b1000 "
b1 #
b10011000 %
b10011000 &
b1 '
b1000 )

#1530000
b1001 "
b0 #
b10011001 %
b10011001 &
b0 '
b1001 )

#1540000
b1010 "
b1111 #
1$
b10011010 %
b10011010 &
b11111 '
b1010 )

#1550000
b1011 "
b1110 #
b10011011 %
b10011011 &
b11110 '
b1011 )

#1560000
b1100 "
b1101 #
b10011100 %
b10011100 &
b11101 '
b1100 )

#1570000
b1101 "
b1100 #
b10011101 %
b10011101 &
b11100 '
b1101 )

#1580000
b1110 "
b1011 #
b10011110 %
b10011110 &
b11011 '
b1110 )

#1590000
b1111 "
b1010 #
b10011111 %
b10011111 &
b11010 '
b1111 )

#1600000
b1010 !
b0 "
0$
b10100000 %
b10100000 &
b1010 '
b1010 (
b0 )

#1610000
b1 "
b1001 #
b10100001 %
b10100001 &
b1001 '
b1 )

#1620000
b10 "
b1000 #
b10100010 %
b10100010 &
b1000 '
b10 )

#1630000
b11 "
b111 #
b10100011 %
b10100011 &
b111 '
b11 )

#1640000
b100 "
b110 #
b10100100 %
b10100100 &
b110 '
b100 )

#1650000
b101 "
b101 #
b10100101 %
b10100101 &
b101 '
b101 )

#1660000
b110 "
b100 #
b10100110 %
b10100110 &
b100 '
b110 )

#1670000
b111 "
b11 #
b10100111 %
b10100111 &
b11 '
b111 )

#1680000
b1000 "
b10 #
b10101000 %
b10101000 &
b10 '
b1000 )

#1690000
b1001 "
b1 #
b10101001 %
b10101001 &
b1 '
b1001 )

#1700000
b1010 "
b0 #
b10101010 %
b10101010 &
b0 '
b1010 )

#1710000
b1011 "
b1111 #
1$
b10101011 %
b10101011 &
b11111 '
b1011 )

#1720000
b1100 "
b1110 #
b10101100 %
b10101100 &
b11110 '
b1100 )

#1730000
b1101 "
b1101 #
b10101101 %
b10101101 &
b11101 '
b1101 )

#1740000
b1110 "
b1100 #
b10101110 %
b10101110 &
b11100 '
b1110 )

#1750000
b1111 "
b1011 #
b10101111 %
b10101111 &
b11011 '
b1111 )

#1760000
b1011 !
b0 "
0$
b10110000 %
b10110000 &
b1011 '
b1011 (
b0 )

#1770000
b1 "
b1010 #
b10110001 %
b10110001 &
b1010 '
b1 )

#1780000
b10 "
b1001 #
b10110010 %
b10110010 &
b1001 '
b10 )

#1790000
b11 "
b1000 #
b10110011 %
b10110011 &
b1000 '
b11 )

#1800000
b100 "
b111 #
b10110100 %
b10110100 &
b111 '
b100 )

#1810000
b101 "
b110 #
b10110101 %
b10110101 &
b110 '
b101 )

#1820000
b110 "
b101 #
b10110110 %
b10110110 &
b101 '
b110 )

#1830000
b111 "
b100 #
b10110111 %
b10110111 &
b100 '
b111 )

#1840000
b1000 "
b11 #
b10111000 %
b10111000 &
b11 '
b1000 )

#1850000
b1001 "
b10 #
b10111001 %
b10111001 &
b10 '
b1001 )

#1860000
b1010 "
b1 #
b10111010 %
b10111010 &
b1 '
b1010 )

#1870000
b1011 "
b0 #
b10111011 %
b10111011 &
b0 '
b1011 )

#1880000
b1100 "
b1111 #
1$
b10111100 %
b10111100 &
b11111 '
b1100 )

#1890000
b1101 "
b1110 #
b10111101 %
b10111101 &
b11110 '
b1101 )

#1900000
b1110 "
b1101 #
b10111110 %
b10111110 &
b11101 '
b1110 )

#1910000
b1111 "
b1100 #
b10111111 %
b10111111 &
b11100 '
b1111 )

#1920000
b1100 !
b0 "
0$
b11000000 %
b11000000 &
b1100 '
b1100 (
b0 )

#1930000
b1 "
b1011 #
b11000001 %
b11000001 &
b1011 '
b1 )

#1940000
b10 "
b1010 #
b11000010 %
b11000010 &
b1010 '
b10 )

#1950000
b11 "
b1001 #
b11000011 %
b11000011 &
b1001 '
b11 )

#1960000
b100 "
b1000 #
b11000100 %
b11000100 &
b1000 '
b100 )

#1970000
b101 "
b111 #
b11000101 %
b11000101 &
b111 '
b101 )

#1980000
b110 "
b110 #
b11000110 %
b11000110 &
b110 '
b110 )

#1990000
b111 "
b101 #
b11000111 %
b11000111 &
b101 '
b111 )

#2000000
b1000 "
b100 #
b11001000 %
b11001000 &
b100 '
b1000 )

#2010000
b1001 "
b11 #
b11001001 %
b11001001 &
b11 '
b1001 )

#2020000
b1010 "
b10 #
b11001010 %
b11001010 &
b10 '
b1010 )

#2030000
b1011 "
b1 #
b11001011 %
b11001011 &
b1 '
b1011 )

#2040000
b1100 "
b0 #
b11001100 %
b11001100 &
b0 '
b1100 )

#2050000
b1101 "
b1111 #
1$
b11001101 %
b11001101 &
b11111 '
b1101 )

#2060000
b1110 "
b1110 #
b11001110 %
b11001110 &
b11110 '
b1110 )

#2070000
b1111 "
b1101 #
b11001111 %
b11001111 &
b11101 '
b1111 )

#2080000
b1101 !
b0 "
0$
b11010000 %
b11010000 &
b1101 '
b1101 (
b0 )

#2090000
b1 "
b1100 #
b11010001 %
b11010001 &
b1100 '
b1 )

#2100000
b10 "
b1011 #
b11010010 %
b11010010 &
b1011 '
b10 )

#2110000
b11 "
b1010 #
b11010011 %
b11010011 &
b1010 '
b11 )

#2120000
b100 "
b1001 #
b11010100 %
b11010100 &
b1001 '
b100 )

#2130000
b101 "
b1000 #
b11010101 %
b11010101 &
b1000 '
b101 )

#2140000
b110 "
b111 #
b11010110 %
b11010110 &
b111 '
b110 )

#2150000
b111 "
b110 #
b11010111 %
b11010111 &
b110 '
b111 )

#2160000
b1000 "
b101 #
b11011000 %
b11011000 &
b101 '
b1000 )

#2170000
b1001 "
b100 #
b11011001 %
b11011001 &
b100 '
b1001 )

#2180000
b1010 "
b11 #
b11011010 %
b11011010 &
b11 '
b1010 )

#2190000
b1011 "
b10 #
b11011011 %
b11011011 &
b10 '
b1011 )

#2200000
b1100 "
b1 #
b11011100 %
b11011100 &
b1 '
b1100 )

#2210000
b1101 "
b0 #
b11011101 %
b11011101 &
b0 '
b1101 )

#2220000
b1110 "
b1111 #
1$
b11011110 %
b11011110 &
b11111 '
b1110 )

#2230000
b1111 "
b1110 #
b11011111 %
b11011111 &
b11110 '
b1111 )

#2240000
b1110 !
b0 "
0$
b11100000 %
b11100000 &
b1110 '
b1110 (
b0 )

#2250000
b1 "
b1101 #
b11100001 %
b11100001 &
b1101 '
b1 )

#2260000
b10 "
b1100 #
b11100010 %
b11100010 &
b1100 '
b10 )

#2270000
b11 "
b1011 #
b11100011 %
b11100011 &
b1011 '
b11 )

#2280000
b100 "
b1010 #
b11100100 %
b11100100 &
b1010 '
b100 )

#2290000
b101 "
b1001 #
b11100101 %
b11100101 &
b1001 '
b101 )

#2300000
b110 "
b1000 #
b11100110 %
b11100110 &
b1000 '
b110 )

#2310000
b111 "
b111 #
b11100111 %
b11100111 &
b111 '
b111 )

#2320000
b1000 "
b110 #
b11101000 %
b11101000 &
b110 '
b1000 )

#2330000
b1001 "
b101 #
b11101001 %
b11101001 &
b101 '
b1001 )

#2340000
b1010 "
b100 #
b11101010 %
b11101010 &
b100 '
b1010 )

#2350000
b1011 "
b11 #
b11101011 %
b11101011 &
b11 '
b1011 )

#2360000
b1100 "
b10 #
b11101100 %
b11101100 &
b10 '
b1100 )

#2370000
b1101 "
b1 #
b11101101 %
b11101101 &
b1 '
b1101 )

#2380000
b1110 "
b0 #
b11101110 %
b11101110 &
b0 '
b1110 )

#2390000
b1111 "
b1111 #
1$
b11101111 %
b11101111 &
b11111 '
b1111 )

#2400000
b1111 !
b0 "
0$
b11110000 %
b11110000 &
b1111 '
b1111 (
b0 )

#2410000
b1 "
b1110 #
b11110001 %
b11110001 &
b1110 '
b1 )

#2420000
b10 "
b1101 #
b11110010 %
b11110010 &
b1101 '
b10 )

#2430000
b11 "
b1100 #
b11110011 %
b11110011 &
b1100 '
b11 )

#2440000
b100 "
b1011 #
b11110100 %
b11110100 &
b1011 '
b100 )

#2450000
b101 "
b1010 #
b11110101 %
b11110101 &
b1010 '
b101 )

#2460000
b110 "
b1001 #
b11110110 %
b11110110 &
b1001 '
b110 )

#2470000
b111 "
b1000 #
b11110111 %
b11110111 &
b1000 '
b111 )

#2480000
b1000 "
b111 #
b11111000 %
b11111000 &
b111 '
b1000 )

#2490000
b1001 "
b110 #
b11111001 %
b11111001 &
b110 '
b1001 )

#2500000
b1010 "
b101 #
b11111010 %
b11111010 &
b101 '
b1010 )

#2510000
b1011 "
b100 #
b11111011 %
b11111011 &
b100 '
b1011 )

#2520000
b1100 "
b11 #
b11111100 %
b11111100 &
b11 '
b1100 )

#2530000
b1101 "
b10 #
b11111101 %
b11111101 &
b10 '
b1101 )

#2540000
b1110 "
b1 #
b11111110 %
b11111110 &
b1 '
b1110 )

#2550000
b1111 "
b0 #
b11111111 %
b11111111 &
b0 '
b1111 )

#2560000
b100000000 %
b100000000 &
